epalgorithmwrapper/__init__.py
epalgorithmwrapper/configuration.json
epalgorithmwrapper/connection.py
epalgorithmwrapper/encapsulation.py
epalgorithmwrapper/main.py
epalgorithmwrapper/api/report.py
epalgorithmwrapper/api/update.py
epalgorithmwrapper/assets/report_template.txt
epalgorithmwrapper/dataprovider/dataprovider.py
epalgorithmwrapper/dataprovider/dataprovider_factory.py
epalgorithmwrapper/datauploader/datauploader.py
epalgorithmwrapper/datauploader/datauploader_factory.py
epalgorithmwrapper/jobprovider/instruction.py
epalgorithmwrapper/jobprovider/job_provider.py
epalgorithmwrapper/jobprovider/job_provider_factory.py
epalgorithmwrapper/jobprovider/message_processor.py
epalgorithmwrapper/jobprovider/rabbitmq_job_provider.py
epalgorithmwrapper/jobprovider/resource_manager.py
epalgorithmwrapper/jobprovider/static_job_provider.py
epalgorithmwrapper/reporter/amtq_reporter.py
epalgorithmwrapper/reporter/reporter.py
epalgorithmwrapper/reporter/reporter_factory.py
epalgorithmwrapper/reporter/rest_api_reporter.py
epalgorithmwrapper/utils/cli_tools.py
epalgorithmwrapper/utils/configuration.py
epalgorithmwrapper/utils/context.py
epalgorithmwrapper/utils/filesystem_utils.py
epalgorithmwrapper/utils/http_tools.py
epalgorithmwrapper/utils/input_provider.py
epalgorithmwrapper/utils/manifest.py
epalgorithmwrapper/utils/message.py
epalgorithmwrapper/validator/validator.py
epalgorithmwrapper-2022.12.22.1623.dist-info/LICENSE
epalgorithmwrapper-2022.12.22.1623.dist-info/METADATA
epalgorithmwrapper-2022.12.22.1623.dist-info/WHEEL
epalgorithmwrapper-2022.12.22.1623.dist-info/top_level.txt
epalgorithmwrapper-2022.12.22.1623.dist-info/RECORD
