Metadata-Version: 2.1
Name: epalgorithmwrapper
Version: 2022.12.22.1623
Requires-Python: >=3.10
License-File: LICENSE
Requires-Dist: pika
Requires-Dist: asset
Requires-Dist: requests
Requires-Dist: eputils
